binance_sdk_dual_investment/__init__.py
binance_sdk_dual_investment/dual_investment.py
binance_sdk_dual_investment/metadata.py
binance_sdk_dual_investment/rest_api/__init__.py
binance_sdk_dual_investment/rest_api/api/__init__.py
binance_sdk_dual_investment/rest_api/api/market_data_api.py
binance_sdk_dual_investment/rest_api/api/trade_api.py
binance_sdk_dual_investment/rest_api/models/__init__.py
binance_sdk_dual_investment/rest_api/models/change_auto_compound_status_response.py
binance_sdk_dual_investment/rest_api/models/check_dual_investment_accounts_response.py
binance_sdk_dual_investment/rest_api/models/enums.py
binance_sdk_dual_investment/rest_api/models/get_dual_investment_positions_response.py
binance_sdk_dual_investment/rest_api/models/get_dual_investment_positions_response_list_inner.py
binance_sdk_dual_investment/rest_api/models/get_dual_investment_product_list_response.py
binance_sdk_dual_investment/rest_api/models/get_dual_investment_product_list_response_list_inner.py
binance_sdk_dual_investment/rest_api/models/subscribe_dual_investment_products_response.py
binance_sdk_dual_investment/rest_api/rest_api.py
binance_sdk_dual_investment-2.2.0.dist-info/METADATA
binance_sdk_dual_investment-2.2.0.dist-info/WHEEL
binance_sdk_dual_investment-2.2.0.dist-info/licenses/LICENCE
binance_sdk_dual_investment-2.2.0.dist-info/RECORD
